pylib_free/__init__.py
pylib_free/core.py
pylib_free-0.0.2.dist-info/licenses/LICENSE
pylib_free-0.0.2.dist-info/METADATA
pylib_free-0.0.2.dist-info/WHEEL
pylib_free-0.0.2.dist-info/top_level.txt
pylib_free-0.0.2.dist-info/RECORD
