Metadata-Version: 2.4
Name: pylib-free
Version: 0.0.2
Summary: Mein erstes Python-Modul
Author-email: PY-libs <Niklassamsel@gmail.com>
License: MIT
Project-URL: Homepage, https://github.com/deinname/pylib-free
Requires-Python: >=3.8
License-File: LICENSE
Dynamic: license-file
